README.md
setup.py
via_sudoku_solver/__init__.py
via_sudoku_solver/__main__.py
via_sudoku_solver/board.py
via_sudoku_solver/cli.py
via_sudoku_solver/game.py
via_sudoku_solver.egg-info/PKG-INFO
via_sudoku_solver.egg-info/SOURCES.txt
via_sudoku_solver.egg-info/dependency_links.txt
via_sudoku_solver.egg-info/entry_points.txt
via_sudoku_solver.egg-info/not-zip-safe
via_sudoku_solver.egg-info/requires.txt
via_sudoku_solver.egg-info/top_level.txt